advoco/__init__.py
advoco/cache.py
advoco/cli.py
advoco/config.py
advoco/connect.py
advoco/do.py
advoco/exceptions.py
advoco/live.py
advoco/sample.py
advoco/tests/__init__.py
advoco/tests/test_grid.py
advoco/tools/grid.py
advoco-0.3.0.dist-info/METADATA
advoco-0.3.0.dist-info/WHEEL
advoco-0.3.0.dist-info/entry_points.txt
advoco-0.3.0.dist-info/RECORD
