Metadata-Version: 2.1
Name: advoco
Version: 0.3.0
Summary: Advent of Code helper library. There are many like it, but this one is mine.
Author: thetaxfraudguy
Author-email: 57653752+thetaxfraudguy@users.noreply.github.com
Requires-Python: >=3.11,<4.0
Classifier: Programming Language :: Python :: 3
Classifier: Programming Language :: Python :: 3.11
Requires-Dist: beautifulsoup4 (>=4.11.1,<5.0.0)
Requires-Dist: click (>=8.1.3,<9.0.0)
Requires-Dist: pytz (>=2022.6,<2023.0)
Requires-Dist: requests (>=2.28.1,<3.0.0)
